Design/CRC.v
/*
MODULE OVERVIEW:
This module computes the Cyclic Redundancy Check for an input bitstream.
The generator polynomial that is used to carry out the polynomial division is x^15 + x^14 + x^10 + x^8 + x^7 + x^4 + x^3 + x^0.
The remainder has 15 bits.
*/

module CRC(
input           clk,        //Clock
input           rst_n,      //active low reset
input           Din,        //serial input
input  [15:0]   size,       //size of the input data packet
output [14:0]   checksum    //remainder of the CRC calculation
);

integer count;
reg [14:0] crc;

always @(posedge clk or negedge rst_n)
begin
 if(~rst_n)
 begin
  crc <= 15'h0000;
  count <= 0;
 end
 else
 begin
  crc[0] <= Din ^ crc[14];
  crc[3] <= crc[2] ^ crc[14];
  crc[4] <= crc[3] ^ crc[14];
  crc[7] <= crc[6] ^ crc[14];
  crc[8] <= crc[7] ^ crc[14];
  crc[10] <= crc[9] ^ crc[14];
  crc[14] <= crc[13] ^ crc[14];

  crc[2:1] <= crc[1:0];
  crc[6:5] <= crc[5:4];
  crc[9] <= crc[8];
  crc[13:11] <= crc[12:10];

  count <= count + 1;
  if(count == size + 14)
  begin
   count <= 0;
   crc <= 15'h0000;
  end
 end
end

assign checksum = (count == size + 14) ? crc : 15'hzzzz;

endmodule

Testbenches/CRC_tb.v


module CRC_tb;

reg clk, rst_n, Din;
reg [15:0] size;

reg [15:0] data;
reg [3:0] ptr;

wire [14:0] checksum;

CRC check (clk, rst_n, Din, size, checksum);

initial
begin
 $dumpfile("../Dumpfiles/CRC_tb.vcd");
 $dumpvars(0, CRC_tb);

 data = 16'habcd;
 ptr = 4'd15;
 size = 15'd16;
 rst_n = 0;
 #10;
 rst_n = 1;
 #130;
 $finish;
end

always
begin
 clk = 1'b1;
 #1;
 clk = 1'b0;
 #1;
end

always @(posedge clk)
begin
 Din = data[ptr];
 if(rst_n)
  ptr <= ptr - 4'd1;
end

endmodule

Dumpfiles/CRC_tb.vcd
$date
	Fri Apr 30 16:41:56 2021
$end
$version
	Icarus Verilog
$end
$timescale
	1s
$end
$scope module CRC_tb $end
$var wire 15 ! checksum [14:0] $end
$var reg 1 " Din $end
$var reg 1 # clk $end
$var reg 16 $ data [15:0] $end
$var reg 4 % ptr [3:0] $end
$var reg 1 & rst_n $end
$var reg 16 ' size [15:0] $end
$scope module check $end
$var wire 1 " Din $end
$var wire 1 # clk $end
$var wire 1 & rst_n $end
$var wire 16 ( size [15:0] $end
$var wire 15 ) checksum [14:0] $end
$var reg 15 * crc [14:0] $end
$var integer 32 + count [31:0] $end
$upscope $end
$upscope $end
$enddefinitions $end
#0
$dumpvars
b0 +
b0 *
bz )
b10000 (
b10000 '
0&
b1111 %
b1010101111001101 $
1#
x"
bz !
$end
#1
0#
#2
1"
1#
#3
0#
#4
1#
#5
0#
#6
1#
#7
0#
#8
1#
#9
0#
#10
b1 +
b1 *
b1110 %
1#
1&
#11
0#
#12
b10 +
b10 *
b1101 %
0"
1#
#13
0#
#14
b11 +
b101 *
b1100 %
1"
1#
#15
0#
#16
b100 +
b1010 *
b1011 %
0"
1#
#17
0#
#18
b101 +
b10101 *
b1010 %
1"
1#
#19
0#
#20
b110 +
b101010 *
b1001 %
0"
1#
#21
0#
#22
b111 +
b1010101 *
b1000 %
1"
1#
#23
0#
#24
b1000 +
b10101011 *
b111 %
1#
#25
0#
#26
b1001 +
b101010111 *
b110 %
1#
#27
0#
#28
b1010 +
b1010101111 *
b101 %
1#
#29
0#
#30
b1011 +
b10101011110 *
b100 %
0"
1#
#31
0#
#32
b1100 +
b101010111100 *
b11 %
1#
#33
0#
#34
b1101 +
b1010101111001 *
b10 %
1"
1#
#35
0#
#36
b1110 +
b10101011110011 *
b1 %
1#
#37
0#
#38
b1111 +
b101010111100110 *
b0 %
0"
1#
#39
0#
#40
b10000 +
b110111001010100 *
b1111 %
1"
1#
#41
0#
#42
b10001 +
b1100100110000 *
b1110 %
1#
#43
0#
#44
b10010 +
b11001001100000 *
b1101 %
0"
1#
#45
0#
#46
b10011 +
b110010011000001 *
b1100 %
1"
1#
#47
0#
#48
b10100 +
b110000011011 *
b1011 %
0"
1#
#49
0#
#50
b10101 +
b1100000110111 *
b1010 %
1"
1#
#51
0#
#52
b10110 +
b11000001101110 *
b1001 %
0"
1#
#53
0#
#54
b10111 +
b110000011011101 *
b1000 %
1"
1#
#55
0#
#56
b11000 +
b10000100010 *
b111 %
1#
#57
0#
#58
b11001 +
b100001000101 *
b110 %
1#
#59
0#
#60
b11010 +
b1000010001011 *
b101 %
1#
#61
0#
#62
b11011 +
b10000100010110 *
b100 %
0"
1#
#63
0#
#64
b11100 +
b100001000101100 *
b11 %
1#
#65
0#
#66
b11101 +
b100000111000000 *
b10 %
1"
1#
#67
0#
#68
b100011000011000 !
b100011000011000 )
b11110 +
b100011000011000 *
b1 %
1#
#69
0#
#70
bz !
bz )
b0 +
b0 *
b0 %
0"
1#
#71
0#
#72
b1 +
b1 *
b1111 %
1"
1#
#73
0#
#74
b10 +
b11 *
b1110 %
1#
#75
0#
#76
b11 +
b110 *
b1101 %
0"
1#
#77
0#
#78
b100 +
b1101 *
b1100 %
1"
1#
#79
0#
#80
b101 +
b11010 *
b1011 %
0"
1#
#81
0#
#82
b110 +
b110101 *
b1010 %
1"
1#
#83
0#
#84
b111 +
b1101010 *
b1001 %
0"
1#
#85
0#
#86
b1000 +
b11010101 *
b1000 %
1"
1#
#87
0#
#88
b1001 +
b110101011 *
b111 %
1#
#89
0#
#90
b1010 +
b1101010111 *
b110 %
1#
#91
0#
#92
b1011 +
b11010101111 *
b101 %
1#
#93
0#
#94
b1100 +
b110101011110 *
b100 %
0"
1#
#95
0#
#96
b1101 +
b1101010111100 *
b11 %
1#
#97
0#
#98
b1110 +
b11010101111001 *
b10 %
1"
1#
#99
0#
#100
b1111 +
b110101011110011 *
b1 %
1#
#101
0#
#102
b10000 +
b1000001111111 *
b0 %
0"
1#
#103
0#
#104
b10001 +
b10000011111111 *
b1111 %
1"
1#
#105
0#
#106
b10010 +
b100000111111111 *
b1110 %
1#
#107
0#
#108
b10011 +
b100011001100111 *
b1101 %
0"
1#
#109
0#
#110
b10100 +
b100100101010110 *
b1100 %
1"
1#
#111
0#
#112
b10101 +
b101011100110101 *
b1011 %
0"
1#
#113
0#
#114
b10110 +
b110101111110010 *
b1010 %
1"
1#
#115
0#
#116
b10111 +
b1001001111101 *
b1001 %
0"
1#
#117
0#
#118
b11000 +
b10010011111011 *
b1000 %
1"
1#
#119
0#
#120
b11001 +
b100100111110111 *
b111 %
1#
#121
0#
#122
b11010 +
b101011001110110 *
b110 %
1#
#123
0#
#124
b11011 +
b110100101110100 *
b101 %
1#
#125
0#
#126
b11100 +
b1011101110001 *
b100 %
0"
1#
#127
0#
#128
b11101 +
b10111011100010 *
b11 %
1#
#129
0#
#130
b101110111000101 !
b101110111000101 )
b11110 +
b101110111000101 *
b10 %
1"
1#
#131
0#
#132
bz !
bz )
b0 +
b0 *
b1 %
1#
#133
0#
#134
b1 +
b0 %
0"
1#
#135
0#
#136
b10 +
b1 *
b1111 %
1"
1#
#137
0#
#138
b11 +
b11 *
b1110 %
1#
#139
0#
#140
b100 +
b110 *
b1101 %
0"
1#
