Design/CRC.v
/*
MODULE OVERVIEW:
This module computes the Cyclic Redundancy Check for an input data byte of length 16 bits or more.
The generator polynomial that is used to carry out the polynomial division is x^15 + x^14 + x^10 + x^8 + x^7 + x^4 + x^3 + x^0,i.e, 1100010110011001.
The remainder has 15 bits.
*/

module CRC(
input           clk,        //Clock
input           rst_n,      //active low reset
input  [23:0]   Din,        //input data packet
input           valid,      //indicates if data is present in the input bus
input  [15:0]   size,       //number of bytes in the input data packet
output [14:0]   checksum    //remainder of the CRC calculation
);

integer shift_count;        //counts the number of left shifts
integer limit;              //maximum value of shift_count
wire finish;                //active high signal to indicate the end of CRC calculation

reg [15:0] crc;                                   //LFSR to implement CRC calculation
reg [15:0] polynomial = 16'b1100010110011001;     //Generator polynomial to perform modulo-2 division

reg CS, NS;
parameter IDLE = 1'b0, FIND = 1'b1;

//Sequential block to update CS state register
always @(posedge clk or negedge rst_n)
begin
 if(~rst_n)
  CS <= IDLE;
 else CS <= NS;
end

//Sequential block to perform CRC calculation
always @(posedge clk or negedge rst_n)
begin
 case(CS)
  IDLE:
  begin
   crc <= (valid) ? (Din >>(8*(size - 2))) : 16'hffff;            //to store the most significant 16 bits in crc if valid is high.
   shift_count <= 0;
  end
  FIND:
  begin
  if(crc[15] == 1'b0)                                             //if MSB is 0, then left shift the contents of crc.
  begin                                                           //During shifting, the LSB of crc must be either loaded with the remaining
   if(shift_count < 8*(size - 2))                                 //most significant bits of input data. After which the LSB will be loaded
    crc <= {crc[14:0],Din[8*(size - 2) - (shift_count + 1)]};     //with zeroes.
   else crc <= crc << 1;
   shift_count <= shift_count + 1;
  end
  else crc <= crc ^ polynomial;                                   //if MSB is 1, then xor the contents of crc with the generator polynomial.
  end
 endcase
end

//Combinatorial block to find NS state register
always @(*)
begin
 limit = 15 + (8*(size - 2));
 case(CS)
  IDLE:
  begin
   if(valid)
    NS = FIND;
   else NS = IDLE;
  end
  FIND:
  begin
   if(finish)
    NS = IDLE;
   else NS = FIND;
  end
  default: NS = IDLE;
 endcase
end

assign finish = ((shift_count == limit) && (crc[15] == 1'b0)) ? 1'b1 : 1'b0;
assign checksum = (finish) ? crc[14:0] : 15'hzzzz;

endmodule

Testbenches/CRC_tb.v


module CRC_tb;

reg clk, rst_n, valid;
reg [15:0] size;
reg [23:0] Din;

wire [14:0] checksum;

CRC check (clk, rst_n, Din, valid, size, checksum);

initial
begin
 $dumpfile("../Dumpfiles/CRC_tb.vcd");
 $dumpvars(0, CRC_tb);

 size = 15'd3;
 rst_n = 0;
 Din = 24'habcdef;
 valid = 0;
 #10;
 rst_n = 1;
 #5;
 valid = 1;
 #5;
 valid = 0;
 #40
 Din = 24'hfedcba;
 valid = 1;
 #100;
 $finish;
end

always
begin
 clk = 1'b1;
 #1;
 clk = 1'b0;
 #1;
end

endmodule

Dumpfiles/CRC_tb.vcd
$date
	Mon May  3 17:04:13 2021
$end
$version
	Icarus Verilog
$end
$timescale
	1s
$end
$scope module CRC_tb $end
$var wire 15 ! checksum [14:0] $end
$var reg 24 " Din [23:0] $end
$var reg 1 # clk $end
$var reg 1 $ rst_n $end
$var reg 16 % size [15:0] $end
$var reg 1 & valid $end
$scope module check $end
$var wire 24 ' Din [23:0] $end
$var wire 1 # clk $end
$var wire 1 $ rst_n $end
$var wire 16 ( size [15:0] $end
$var wire 1 & valid $end
$var wire 1 ) finish $end
$var wire 15 * checksum [14:0] $end
$var reg 1 + CS $end
$var reg 1 , NS $end
$var reg 16 - crc [15:0] $end
$var reg 16 . polynomial [15:0] $end
$var integer 32 / limit [31:0] $end
$var integer 32 0 shift_count [31:0] $end
$upscope $end
$upscope $end
$enddefinitions $end
#0
$dumpvars
bx 0
b10111 /
b1100010110011001 .
bx -
0,
0+
bx *
x)
b11 (
b101010111100110111101111 '
0&
b11 %
0$
1#
b101010111100110111101111 "
bx !
$end
#1
0#
#2
bz !
bz *
0)
b0 0
b1111111111111111 -
1#
#3
0#
#4
1#
#5
0#
#6
1#
#7
0#
#8
1#
#9
0#
#10
1#
1$
#11
0#
#12
1#
#13
0#
#14
1#
#15
1,
0#
1&
#16
1+
b1010101111001101 -
1#
#17
0#
#18
b110111001010100 -
1#
#19
0#
#20
b1 0
b1101110010101001 -
1#
0&
#21
0#
#22
b1100100110000 -
1#
#23
0#
#24
b10 0
b11001001100001 -
1#
#25
0#
#26
b11 0
b110010011000011 -
1#
#27
0#
#28
b100 0
b1100100110000110 -
1#
#29
0#
#30
b110000011111 -
1#
#31
0#
#32
b101 0
b1100000111111 -
1#
#33
0#
#34
b110 0
b11000001111111 -
1#
#35
0#
#36
b111 0
b110000011111111 -
1#
#37
0#
#38
b1000 0
b1100000111111111 -
1#
#39
0#
#40
b10001100110 -
1#
#41
0#
#42
b1001 0
b100011001100 -
1#
#43
0#
#44
b1010 0
b1000110011000 -
1#
#45
0#
#46
b1011 0
b10001100110000 -
1#
#47
0#
#48
b1100 0
b100011001100000 -
1#
#49
0#
#50
b1101 0
b1000110011000000 -
1#
#51
0#
#52
b100100101011001 -
1#
#53
0#
#54
b1110 0
b1001001010110010 -
1#
#55
0#
#56
b101011100101011 -
1#
#57
0#
#58
b1111 0
b1010111001010110 -
1#
#59
0#
#60
b110101111001111 -
1#
1&
b111111101101110010111010 "
b111111101101110010111010 '
#61
0#
#62
b10000 0
b1101011110011110 -
1#
#63
0#
#64
b1001000000111 -
1#
#65
0#
#66
b10001 0
b10010000001110 -
1#
#67
0#
#68
b10010 0
b100100000011100 -
1#
#69
0#
#70
b10011 0
b1001000000111000 -
1#
#71
0#
#72
b101010110100001 -
1#
#73
0#
#74
b10100 0
b1010101101000010 -
1#
#75
0#
#76
b110111011011011 -
1#
#77
0#
#78
b10101 0
b1101110110110110 -
1#
#79
0#
#80
b1100000101111 -
1#
#81
0#
#82
b10110 0
b11000001011110 -
1#
#83
0#
#84
b110000010111100 !
b110000010111100 *
0,
1)
b10111 0
b110000010111100 -
1#
#85
0#
#86
0)
bz !
bz *
1,
b11000 0
b1100000101111000 -
0+
1#
#87
0#
#88
1+
b0 0
b1111111011011100 -
1#
#89
0#
#90
b11101101000101 -
1#
#91
0#
#92
b1 0
b111011010001011 -
1#
#93
0#
#94
b10 0
b1110110100010110 -
1#
#95
0#
#96
b10100010001111 -
1#
#97
0#
#98
b11 0
b101000100011111 -
1#
#99
0#
#100
b100 0
b1010001000111111 -
1#
#101
0#
#102
b110011110100110 -
1#
#103
0#
#104
b101 0
b1100111101001101 -
1#
#105
0#
#106
b101011010100 -
1#
#107
0#
#108
b110 0
b1010110101000 -
1#
#109
0#
#110
b111 0
b10101101010001 -
1#
#111
0#
#112
b1000 0
b101011010100010 -
1#
#113
0#
#114
b1001 0
b1010110101000100 -
1#
#115
0#
#116
b110100011011101 -
1#
#117
0#
#118
b1010 0
b1101000110111010 -
1#
#119
0#
#120
b1010000100011 -
1#
#121
0#
#122
b1011 0
b10100001000110 -
1#
#123
0#
#124
b1100 0
b101000010001100 -
1#
#125
0#
#126
b1101 0
b1010000100011000 -
1#
#127
0#
#128
b110010010000001 -
1#
#129
0#
#130
b1110 0
b1100100100000010 -
1#
#131
0#
#132
b110010011011 -
1#
#133
0#
#134
b1111 0
b1100100110110 -
1#
#135
0#
#136
b10000 0
b11001001101100 -
1#
#137
0#
#138
b10001 0
b110010011011000 -
1#
#139
0#
#140
b10010 0
b1100100110110000 -
1#
#141
0#
#142
b110000101001 -
1#
#143
0#
#144
b10011 0
b1100001010010 -
1#
#145
0#
#146
b10100 0
b11000010100100 -
1#
#147
0#
#148
b10101 0
b110000101001000 -
1#
#149
0#
#150
b10110 0
b1100001010010000 -
1#
#151
0#
#152
b11100001001 -
1#
#153
0#
#154
b111000010010 !
b111000010010 *
0,
1)
b10111 0
b111000010010 -
1#
#155
0#
#156
0)
bz !
bz *
1,
0+
b11000 0
b1110000100100 -
1#
#157
0#
#158
b0 0
b1111111011011100 -
1+
1#
#159
0#
#160
b11101101000101 -
1#
