Design/memory.v
/*
MODULE OVERVIEW:
This module represents the intelligent memory of the CC770.
*/

module memory (
input            clk,        //clock
input            rst_n,      //active low reset
input            rw,         //read(1) or write(0)
input  [7:0]     addr,       //read and write address
input  [7:0]     Din,        //input data bus
output [7:0]     Dout        //output data bus
);

reg [7:0] registers[0:255];             //internal register array

integer i;                              //loop variable to address the register array

always @(posedge clk or negedge rst_n)
begin
 if(~rst_n)
 begin
  for(i = 0; i < 256; i = i + 1)
   registers[i] <= 8'h00;                               //clearing all the contents of the array
 end
 else if(~rw)
  registers[addr] <= Din;                               //writing into the register
end

assign Dout = (rw) ? registers[addr] : 8'hzz;           //reading from the register

endmodule

Testbenches/memory_tb.v
/*
Testbench for intelligent memory.
*/

module memory_tb;

//inputs
reg            clk;        //clock
reg            rst_n;     //active low reset
reg            rw;         //read(1) or write(0)
reg  [7:0]     addr;     //read and write address
reg  [7:0]     Din;        //input data bus

//output
wire [7:0]     Dout ;       //output data bus

integer error, i ; //end of test flag

localparam period = 10;

memory uut (.clk(clk), .rst_n(rst_n), .rw(rw), .addr(addr), .Din(Din), .Dout(Dout));

initial begin
$dumpfile("../Dumpfiles/memory_tb.vcd");
$dumpvars(0, memory_tb);

rst_n = 1 ;
clk = 0 ;
rw = 1 ;
addr = 8'h00;
Din = 8'h00 ;
addr = 0;
error = 0;


#5;
//write
rw = 0 ;
repeat(256) begin
 Din = Din + 8'h01 ;
 #20;
 addr = addr + 8'h01 ;
 end

//read
rw = 1 ;

for(i = 0; i < 256; i = i + 1) begin
 #10;
 if(Dout == i)
 error = error + 1 ;
 #10;
 addr = addr + 8'h01 ;
 end

//reset
rst_n = 0 ;
for(i = 0; i < 256; i = i + 1) begin
 #10;
 if(Dout != 8'h00)
 error = error + 1 ;
 #10;
 addr = addr + 8'h01 ;
 end

//random write and read
rst_n = 1;
rw = 0 ;
addr = 8'h55 ;
Din = 8'h55 ;
#20;

addr = 8'hAA ;
Din = 8'hAA ;
#20 ;

rw = 1;
addr = 8'h55 ;
#10;
if(Dout != 8'h55)
error = error + 1;
#10;

addr = 8'hAA ;
#10;
if(Dout != 8'hAA)
error = error + 1;
#10;

//trying to write and read while in reset
rst_n = 0;
rw = 0;
addr = 8'hEE ;
Din = 8'hEE ;
#20;

addr = 8'hBB ;
Din = 8'hBB ;
#20;

rw = 1 ;
addr = 8'hEE ;
#10;
if(Dout != 8'hEE)
error = error + 1;
#10;

addr = 8'hEE ;
#10;
if(Dout != 8'hEE)
error = error + 1;
#10;

$finish;

end


always
 #period clk = ~clk ;


endmodule

Dumpfiles/memory_tb.vcd
$date
	Sat May 29 21:51:22 2021
$end
$version
	Icarus Verilog
$end
$timescale
	1s
$end
$scope module memory_tb $end
$var wire 8 ! Dout [7:0] $end
$var reg 8 " Din [7:0] $end
$var reg 8 # addr [7:0] $end
$var reg 1 $ clk $end
$var reg 1 % rst_n $end
$var reg 1 & rw $end
$var integer 32 ' error [31:0] $end
$var integer 32 ( i [31:0] $end
$scope module uut $end
$var wire 8 ) Din [7:0] $end
$var wire 8 * addr [7:0] $end
$var wire 1 $ clk $end
$var wire 1 % rst_n $end
$var wire 1 & rw $end
$var wire 8 + Dout [7:0] $end
$var integer 32 , i [31:0] $end
$upscope $end
$upscope $end
$enddefinitions $end
#0
$dumpvars
bx ,
bx +
b0 *
b0 )
bx (
b0 '
1&
1%
0$
b0 #
b0 "
bx !
$end
#5
bz !
bz +
b1 "
b1 )
0&
#10
1$
#20
0$
#25
b10 "
b10 )
b1 #
b1 *
#30
1$
#40
0$
#45
b11 "
b11 )
b10 #
b10 *
#50
1$
#60
0$
#65
b100 "
b100 )
b11 #
b11 *
#70
1$
#80
0$
#85
b101 "
b101 )
b100 #
b100 *
#90
1$
#100
0$
#105
b110 "
b110 )
b101 #
b101 *
#110
1$
#120
0$
#125
b111 "
b111 )
b110 #
b110 *
#130
1$
#140
0$
#145
b1000 "
b1000 )
b111 #
b111 *
#150
1$
#160
0$
#165
b1001 "
b1001 )
b1000 #
b1000 *
#170
1$
#180
0$
#185
b1010 "
b1010 )
b1001 #
b1001 *
#190
1$
#200
0$
#205
b1011 "
b1011 )
b1010 #
b1010 *
#210
1$
#220
0$
#225
b1100 "
b1100 )
b1011 #
b1011 *
#230
1$
#240
0$
#245
b1101 "
b1101 )
b1100 #
b1100 *
#250
1$
#260
0$
#265
b1110 "
b1110 )
b1101 #
b1101 *
#270
1$
#280
0$
#285
b1111 "
b1111 )
b1110 #
b1110 *
#290
1$
#300
0$
#305
b10000 "
b10000 )
b1111 #
b1111 *
#310
1$
#320
0$
#325
b10001 "
b10001 )
b10000 #
b10000 *
#330
1$
#340
0$
#345
b10010 "
b10010 )
b10001 #
b10001 *
#350
1$
#360
0$
#365
b10011 "
b10011 )
b10010 #
b10010 *
#370
1$
#380
0$
#385
b10100 "
b10100 )
b10011 #
b10011 *
#390
1$
#400
0$
#405
b10101 "
b10101 )
b10100 #
b10100 *
#410
1$
#420
0$
#425
b10110 "
b10110 )
b10101 #
b10101 *
#430
1$
#440
0$
#445
b10111 "
b10111 )
b10110 #
b10110 *
#450
1$
#460
0$
#465
b11000 "
b11000 )
b10111 #
b10111 *
#470
1$
#480
0$
#485
b11001 "
b11001 )
b11000 #
b11000 *
#490
1$
#500
0$
#505
b11010 "
b11010 )
b11001 #
b11001 *
#510
1$
#520
0$
#525
b11011 "
b11011 )
b11010 #
b11010 *
#530
1$
#540
0$
#545
b11100 "
b11100 )
b11011 #
b11011 *
#550
1$
#560
0$
#565
b11101 "
b11101 )
b11100 #
b11100 *
#570
1$
#580
0$
#585
b11110 "
b11110 )
b11101 #
b11101 *
#590
1$
#600
0$
#605
b11111 "
b11111 )
b11110 #
b11110 *
#610
1$
#620
0$
#625
b100000 "
b100000 )
b11111 #
b11111 *
#630
1$
#640
0$
#645
b100001 "
b100001 )
b100000 #
b100000 *
#650
1$
#660
0$
#665
b100010 "
b100010 )
b100001 #
b100001 *
#670
1$
#680
0$
#685
b100011 "
b100011 )
b100010 #
b100010 *
#690
1$
#700
0$
#705
b100100 "
b100100 )
b100011 #
b100011 *
#710
1$
#720
0$
#725
b100101 "
b100101 )
b100100 #
b100100 *
#730
1$
#740
0$
#745
b100110 "
b100110 )
b100101 #
b100101 *
#750
1$
#760
0$
#765
b100111 "
b100111 )
b100110 #
b100110 *
#770
1$
#780
0$
#785
b101000 "
b101000 )
b100111 #
b100111 *
#790
1$
#800
0$
#805
b101001 "
b101001 )
b101000 #
b101000 *
#810
1$
#820
0$
#825
b101010 "
b101010 )
b101001 #
b101001 *
#830
1$
#840
0$
#845
b101011 "
b101011 )
b101010 #
b101010 *
#850
1$
#860
0$
#865
b101100 "
b101100 )
b101011 #
b101011 *
#870
1$
#880
0$
#885
b101101 "
b101101 )
b101100 #
b101100 *
#890
1$
#900
0$
#905
b101110 "
b101110 )
b101101 #
b101101 *
#910
1$
#920
0$
#925
b101111 "
b101111 )
b101110 #
b101110 *
#930
1$
#940
0$
#945
b110000 "
b110000 )
b101111 #
b101111 *
#950
1$
#960
0$
#965
b110001 "
b110001 )
b110000 #
b110000 *
#970
1$
#980
0$
#985
b110010 "
b110010 )
b110001 #
b110001 *
#990
1$
#1000
0$
#1005
b110011 "
b110011 )
b110010 #
b110010 *
#1010
1$
#1020
0$
#1025
b110100 "
b110100 )
b110011 #
b110011 *
#1030
1$
#1040
0$
#1045
b110101 "
b110101 )
b110100 #
b110100 *
#1050
1$
#1060
0$
#1065
b110110 "
b110110 )
b110101 #
b110101 *
#1070
1$
#1080
0$
#1085
b110111 "
b110111 )
b110110 #
b110110 *
#1090
1$
#1100
0$
#1105
b111000 "
b111000 )
b110111 #
b110111 *
#1110
1$
#1120
0$
#1125
b111001 "
b111001 )
b111000 #
b111000 *
#1130
1$
#1140
0$
#1145
b111010 "
b111010 )
b111001 #
b111001 *
#1150
1$
#1160
0$
#1165
b111011 "
b111011 )
b111010 #
b111010 *
#1170
1$
#1180
0$
#1185
b111100 "
b111100 )
b111011 #
b111011 *
#1190
1$
#1200
0$
#1205
b111101 "
b111101 )
b111100 #
b111100 *
#1210
1$
#1220
0$
#1225
b111110 "
b111110 )
b111101 #
b111101 *
#1230
1$
#1240
0$
#1245
b111111 "
b111111 )
b111110 #
b111110 *
#1250
1$
#1260
0$
#1265
b1000000 "
b1000000 )
b111111 #
b111111 *
#1270
1$
#1280
0$
#1285
b1000001 "
b1000001 )
b1000000 #
b1000000 *
#1290
1$
#1300
0$
#1305
b1000010 "
b1000010 )
b1000001 #
b1000001 *
#1310
1$
#1320
0$
#1325
b1000011 "
b1000011 )
b1000010 #
b1000010 *
#1330
1$
#1340
0$
#1345
b1000100 "
b1000100 )
b1000011 #
b1000011 *
#1350
1$
#1360
0$
#1365
b1000101 "
b1000101 )
b1000100 #
b1000100 *
#1370
1$
#1380
0$
#1385
b1000110 "
b1000110 )
b1000101 #
b1000101 *
#1390
1$
#1400
0$
#1405
b1000111 "
b1000111 )
b1000110 #
b1000110 *
#1410
1$
#1420
0$
#1425
b1001000 "
b1001000 )
b1000111 #
b1000111 *
#1430
1$
#1440
0$
#1445
b1001001 "
b1001001 )
b1001000 #
b1001000 *
#1450
1$
#1460
0$
#1465
b1001010 "
b1001010 )
b1001001 #
b1001001 *
#1470
1$
#1480
0$
#1485
b1001011 "
b1001011 )
b1001010 #
b1001010 *
#1490
1$
#1500
0$
#1505
b1001100 "
b1001100 )
b1001011 #
b1001011 *
#1510
1$
#1520
0$
#1525
b1001101 "
b1001101 )
b1001100 #
b1001100 *
#1530
1$
#1540
0$
#1545
b1001110 "
b1001110 )
b1001101 #
b1001101 *
#1550
1$
#1560
0$
#1565
b1001111 "
b1001111 )
b1001110 #
b1001110 *
#1570
1$
#1580
0$
#1585
b1010000 "
b1010000 )
b1001111 #
b1001111 *
#1590
1$
#1600
0$
#1605
b1010001 "
b1010001 )
b1010000 #
b1010000 *
#1610
1$
#1620
0$
#1625
b1010010 "
b1010010 )
b1010001 #
b1010001 *
#1630
1$
#1640
0$
#1645
b1010011 "
b1010011 )
b1010010 #
b1010010 *
#1650
1$
#1660
0$
#1665
b1010100 "
b1010100 )
b1010011 #
b1010011 *
#1670
1$
#1680
0$
#1685
b1010101 "
b1010101 )
b1010100 #
b1010100 *
#1690
1$
#1700
0$
#1705
b1010110 "
b1010110 )
b1010101 #
b1010101 *
#1710
1$
#1720
0$
#1725
b1010111 "
b1010111 )
b1010110 #
b1010110 *
#1730
1$
#1740
0$
#1745
b1011000 "
b1011000 )
b1010111 #
b1010111 *
#1750
1$
#1760
0$
#1765
b1011001 "
b1011001 )
b1011000 #
b1011000 *
#1770
1$
#1780
0$
#1785
b1011010 "
b1011010 )
b1011001 #
b1011001 *
#1790
1$
#1800
0$
#1805
b1011011 "
b1011011 )
b1011010 #
b1011010 *
#1810
1$
#1820
0$
#1825
b1011100 "
b1011100 )
b1011011 #
b1011011 *
#1830
1$
#1840
0$
#1845
b1011101 "
b1011101 )
b1011100 #
b1011100 *
#1850
1$
#1860
0$
#1865
b1011110 "
b1011110 )
b1011101 #
b1011101 *
#1870
1$
#1880
0$
#1885
b1011111 "
b1011111 )
b1011110 #
b1011110 *
#1890
1$
#1900
0$
#1905
b1100000 "
b1100000 )
b1011111 #
b1011111 *
#1910
1$
#1920
0$
#1925
b1100001 "
b1100001 )
b1100000 #
b1100000 *
#1930
1$
#1940
0$
#1945
b1100010 "
b1100010 )
b1100001 #
b1100001 *
#1950
1$
#1960
0$
#1965
b1100011 "
b1100011 )
b1100010 #
b1100010 *
#1970
1$
#1980
0$
#1985
b1100100 "
b1100100 )
b1100011 #
b1100011 *
#1990
1$
#2000
0$
#2005
b1100101 "
b1100101 )
b1100100 #
b1100100 *
#2010
1$
#2020
0$
#2025
b1100110 "
b1100110 )
b1100101 #
b1100101 *
#2030
1$
#2040
0$
#2045
b1100111 "
b1100111 )
b1100110 #
b1100110 *
#2050
1$
#2060
0$
#2065
b1101000 "
b1101000 )
b1100111 #
b1100111 *
#2070
1$
#2080
0$
#2085
b1101001 "
b1101001 )
b1101000 #
b1101000 *
#2090
1$
#2100
0$
#2105
b1101010 "
b1101010 )
b1101001 #
b1101001 *
#2110
1$
#2120
0$
#2125
b1101011 "
b1101011 )
b1101010 #
b1101010 *
#2130
1$
#2140
0$
#2145
b1101100 "
b1101100 )
b1101011 #
b1101011 *
#2150
1$
#2160
0$
#2165
b1101101 "
b1101101 )
b1101100 #
b1101100 *
#2170
1$
#2180
0$
#2185
b1101110 "
b1101110 )
b1101101 #
b1101101 *
#2190
1$
#2200
0$
#2205
b1101111 "
b1101111 )
b1101110 #
b1101110 *
#2210
1$
#2220
0$
#2225
b1110000 "
b1110000 )
b1101111 #
b1101111 *
#2230
1$
#2240
0$
#2245
b1110001 "
b1110001 )
b1110000 #
b1110000 *
#2250
1$
#2260
0$
#2265
b1110010 "
b1110010 )
b1110001 #
b1110001 *
#2270
1$
#2280
0$
#2285
b1110011 "
b1110011 )
b1110010 #
b1110010 *
#2290
1$
#2300
0$
#2305
b1110100 "
b1110100 )
b1110011 #
b1110011 *
#2310
1$
#2320
0$
#2325
b1110101 "
b1110101 )
b1110100 #
b1110100 *
#2330
1$
#2340
0$
#2345
b1110110 "
b1110110 )
b1110101 #
b1110101 *
#2350
1$
#2360
0$
#2365
b1110111 "
b1110111 )
b1110110 #
b1110110 *
#2370
1$
#2380
0$
#2385
b1111000 "
b1111000 )
b1110111 #
b1110111 *
#2390
1$
#2400
0$
#2405
b1111001 "
b1111001 )
b1111000 #
b1111000 *
#2410
1$
#2420
0$
#2425
b1111010 "
b1111010 )
b1111001 #
b1111001 *
#2430
1$
#2440
0$
#2445
b1111011 "
b1111011 )
b1111010 #
b1111010 *
#2450
1$
#2460
0$
#2465
b1111100 "
b1111100 )
b1111011 #
b1111011 *
#2470
1$
#2480
0$
#2485
b1111101 "
b1111101 )
b1111100 #
b1111100 *
#2490
1$
#2500
0$
#2505
b1111110 "
b1111110 )
b1111101 #
b1111101 *
#2510
1$
#2520
0$
#2525
b1111111 "
b1111111 )
b1111110 #
b1111110 *
#2530
1$
#2540
0$
#2545
b10000000 "
b10000000 )
b1111111 #
b1111111 *
#2550
1$
#2560
0$
#2565
b10000001 "
b10000001 )
b10000000 #
b10000000 *
#2570
1$
#2580
0$
#2585
b10000010 "
b10000010 )
b10000001 #
b10000001 *
#2590
1$
#2600
0$
#2605
b10000011 "
b10000011 )
b10000010 #
b10000010 *
#2610
1$
#2620
0$
#2625
b10000100 "
b10000100 )
b10000011 #
b10000011 *
#2630
1$
#2640
0$
#2645
b10000101 "
b10000101 )
b10000100 #
b10000100 *
#2650
1$
#2660
0$
#2665
b10000110 "
b10000110 )
b10000101 #
b10000101 *
#2670
1$
#2680
0$
#2685
b10000111 "
b10000111 )
b10000110 #
b10000110 *
#2690
1$
#2700
0$
#2705
b10001000 "
b10001000 )
b10000111 #
b10000111 *
#2710
1$
#2720
0$
#2725
b10001001 "
b10001001 )
b10001000 #
b10001000 *
#2730
1$
#2740
0$
#2745
b10001010 "
b10001010 )
b10001001 #
b10001001 *
#2750
1$
#2760
0$
#2765
b10001011 "
b10001011 )
b10001010 #
b10001010 *
#2770
1$
#2780
0$
#2785
b10001100 "
b10001100 )
b10001011 #
b10001011 *
#2790
1$
#2800
0$
#2805
b10001101 "
b10001101 )
b10001100 #
b10001100 *
#2810
1$
#2820
0$
#2825
b10001110 "
b10001110 )
b10001101 #
b10001101 *
#2830
1$
#2840
0$
#2845
b10001111 "
b10001111 )
b10001110 #
b10001110 *
#2850
1$
#2860
0$
#2865
b10010000 "
b10010000 )
b10001111 #
b10001111 *
#2870
1$
#2880
0$
#2885
b10010001 "
b10010001 )
b10010000 #
b10010000 *
#2890
1$
#2900
0$
#2905
b10010010 "
b10010010 )
b10010001 #
b10010001 *
#2910
1$
#2920
0$
#2925
b10010011 "
b10010011 )
b10010010 #
b10010010 *
#2930
1$
#2940
0$
#2945
b10010100 "
b10010100 )
b10010011 #
b10010011 *
#2950
1$
#2960
0$
#2965
b10010101 "
b10010101 )
b10010100 #
b10010100 *
#2970
1$
#2980
0$
#2985
b10010110 "
b10010110 )
b10010101 #
b10010101 *
#2990
1$
#3000
0$
#3005
b10010111 "
b10010111 )
b10010110 #
b10010110 *
#3010
1$
#3020
0$
#3025
b10011000 "
b10011000 )
b10010111 #
b10010111 *
#3030
1$
#3040
0$
#3045
b10011001 "
b10011001 )
b10011000 #
b10011000 *
#3050
1$
#3060
0$
#3065
b10011010 "
b10011010 )
b10011001 #
b10011001 *
#3070
1$
#3080
0$
#3085
b10011011 "
b10011011 )
b10011010 #
b10011010 *
#3090
1$
#3100
0$
#3105
b10011100 "
b10011100 )
b10011011 #
b10011011 *
#3110
1$
#3120
0$
#3125
b10011101 "
b10011101 )
b10011100 #
b10011100 *
#3130
1$
#3140
0$
#3145
b10011110 "
b10011110 )
b10011101 #
b10011101 *
#3150
1$
#3160
0$
#3165
b10011111 "
b10011111 )
b10011110 #
b10011110 *
#3170
1$
#3180
0$
#3185
b10100000 "
b10100000 )
b10011111 #
b10011111 *
#3190
1$
#3200
0$
#3205
b10100001 "
b10100001 )
b10100000 #
b10100000 *
#3210
1$
#3220
0$
#3225
b10100010 "
b10100010 )
b10100001 #
b10100001 *
#3230
1$
#3240
0$
#3245
b10100011 "
b10100011 )
b10100010 #
b10100010 *
#3250
1$
#3260
0$
#3265
b10100100 "
b10100100 )
b10100011 #
b10100011 *
#3270
1$
#3280
0$
#3285
b10100101 "
b10100101 )
b10100100 #
b10100100 *
#3290
1$
#3300
0$
#3305
b10100110 "
b10100110 )
b10100101 #
b10100101 *
#3310
1$
#3320
0$
#3325
b10100111 "
b10100111 )
b10100110 #
b10100110 *
#3330
1$
#3340
0$
#3345
b10101000 "
b10101000 )
b10100111 #
b10100111 *
#3350
1$
#3360
0$
#3365
b10101001 "
b10101001 )
b10101000 #
b10101000 *
#3370
1$
#3380
0$
#3385
b10101010 "
b10101010 )
b10101001 #
b10101001 *
#3390
1$
#3400
0$
#3405
b10101011 "
b10101011 )
b10101010 #
b10101010 *
#3410
1$
#3420
0$
#3425
b10101100 "
b10101100 )
b10101011 #
b10101011 *
#3430
1$
#3440
0$
#3445
b10101101 "
b10101101 )
b10101100 #
b10101100 *
#3450
1$
#3460
0$
#3465
b10101110 "
b10101110 )
b10101101 #
b10101101 *
#3470
1$
#3480
0$
#3485
b10101111 "
b10101111 )
b10101110 #
b10101110 *
#3490
1$
#3500
0$
#3505
b10110000 "
b10110000 )
b10101111 #
b10101111 *
#3510
1$
#3520
0$
#3525
b10110001 "
b10110001 )
b10110000 #
b10110000 *
#3530
1$
#3540
0$
#3545
b10110010 "
b10110010 )
b10110001 #
b10110001 *
#3550
1$
#3560
0$
#3565
b10110011 "
b10110011 )
b10110010 #
b10110010 *
#3570
1$
#3580
0$
#3585
b10110100 "
b10110100 )
b10110011 #
b10110011 *
#3590
1$
#3600
0$
#3605
b10110101 "
b10110101 )
b10110100 #
b10110100 *
#3610
1$
#3620
0$
#3625
b10110110 "
b10110110 )
b10110101 #
b10110101 *
#3630
1$
#3640
0$
#3645
b10110111 "
b10110111 )
b10110110 #
b10110110 *
#3650
1$
#3660
0$
#3665
b10111000 "
b10111000 )
b10110111 #
b10110111 *
#3670
1$
#3680
0$
#3685
b10111001 "
b10111001 )
b10111000 #
b10111000 *
#3690
1$
#3700
0$
#3705
b10111010 "
b10111010 )
b10111001 #
b10111001 *
#3710
1$
#3720
0$
#3725
b10111011 "
b10111011 )
b10111010 #
b10111010 *
#3730
1$
#3740
0$
#3745
b10111100 "
b10111100 )
b10111011 #
b10111011 *
#3750
1$
#3760
0$
#3765
b10111101 "
b10111101 )
b10111100 #
b10111100 *
#3770
1$
#3780
0$
#3785
b10111110 "
b10111110 )
b10111101 #
b10111101 *
#3790
1$
#3800
0$
#3805
b10111111 "
b10111111 )
b10111110 #
b10111110 *
#3810
1$
#3820
0$
#3825
b11000000 "
b11000000 )
b10111111 #
b10111111 *
#3830
1$
#3840
0$
#3845
b11000001 "
b11000001 )
b11000000 #
b11000000 *
#3850
1$
#3860
0$
#3865
b11000010 "
b11000010 )
b11000001 #
b11000001 *
#3870
1$
#3880
0$
#3885
b11000011 "
b11000011 )
b11000010 #
b11000010 *
#3890
1$
#3900
0$
#3905
b11000100 "
b11000100 )
b11000011 #
b11000011 *
#3910
1$
#3920
0$
#3925
b11000101 "
b11000101 )
b11000100 #
b11000100 *
#3930
1$
#3940
0$
#3945
b11000110 "
b11000110 )
b11000101 #
b11000101 *
#3950
1$
#3960
0$
#3965
b11000111 "
b11000111 )
b11000110 #
b11000110 *
#3970
1$
#3980
0$
#3985
b11001000 "
b11001000 )
b11000111 #
b11000111 *
#3990
1$
#4000
0$
#4005
b11001001 "
b11001001 )
b11001000 #
b11001000 *
#4010
1$
#4020
0$
#4025
b11001010 "
b11001010 )
b11001001 #
b11001001 *
#4030
1$
#4040
0$
#4045
b11001011 "
b11001011 )
b11001010 #
b11001010 *
#4050
1$
#4060
0$
#4065
b11001100 "
b11001100 )
b11001011 #
b11001011 *
#4070
1$
#4080
0$
#4085
b11001101 "
b11001101 )
b11001100 #
b11001100 *
#4090
1$
#4100
0$
#4105
b11001110 "
b11001110 )
b11001101 #
b11001101 *
#4110
1$
#4120
0$
#4125
b11001111 "
b11001111 )
b11001110 #
b11001110 *
#4130
1$
#4140
0$
#4145
b11010000 "
b11010000 )
b11001111 #
b11001111 *
#4150
1$
#4160
0$
#4165
b11010001 "
b11010001 )
b11010000 #
b11010000 *
#4170
1$
#4180
0$
#4185
b11010010 "
b11010010 )
b11010001 #
b11010001 *
#4190
1$
#4200
0$
#4205
b11010011 "
b11010011 )
b11010010 #
b11010010 *
#4210
1$
#4220
0$
#4225
b11010100 "
b11010100 )
b11010011 #
b11010011 *
#4230
1$
#4240
0$
#4245
b11010101 "
b11010101 )
b11010100 #
b11010100 *
#4250
1$
#4260
0$
#4265
b11010110 "
b11010110 )
b11010101 #
b11010101 *
#4270
1$
#4280
0$
#4285
b11010111 "
b11010111 )
b11010110 #
b11010110 *
#4290
1$
#4300
0$
#4305
b11011000 "
b11011000 )
b11010111 #
b11010111 *
#4310
1$
#4320
0$
#4325
b11011001 "
b11011001 )
b11011000 #
b11011000 *
#4330
1$
#4340
0$
#4345
b11011010 "
b11011010 )
b11011001 #
b11011001 *
#4350
1$
#4360
0$
#4365
b11011011 "
b11011011 )
b11011010 #
b11011010 *
#4370
1$
#4380
0$
#4385
b11011100 "
b11011100 )
b11011011 #
b11011011 *
#4390
1$
#4400
0$
#4405
b11011101 "
b11011101 )
b11011100 #
b11011100 *
#4410
1$
#4420
0$
#4425
b11011110 "
b11011110 )
b11011101 #
b11011101 *
#4430
1$
#4440
0$
#4445
b11011111 "
b11011111 )
b11011110 #
b11011110 *
#4450
1$
#4460
0$
#4465
b11100000 "
b11100000 )
b11011111 #
b11011111 *
#4470
1$
#4480
0$
#4485
b11100001 "
b11100001 )
b11100000 #
b11100000 *
#4490
1$
#4500
0$
#4505
b11100010 "
b11100010 )
b11100001 #
b11100001 *
#4510
1$
#4520
0$
#4525
b11100011 "
b11100011 )
b11100010 #
b11100010 *
#4530
1$
#4540
0$
#4545
b11100100 "
b11100100 )
b11100011 #
b11100011 *
#4550
1$
#4560
0$
#4565
b11100101 "
b11100101 )
b11100100 #
b11100100 *
#4570
1$
#4580
0$
#4585
b11100110 "
b11100110 )
b11100101 #
b11100101 *
#4590
1$
#4600
0$
#4605
b11100111 "
b11100111 )
b11100110 #
b11100110 *
#4610
1$
#4620
0$
#4625
b11101000 "
b11101000 )
b11100111 #
b11100111 *
#4630
1$
#4640
0$
#4645
b11101001 "
b11101001 )
b11101000 #
b11101000 *
#4650
1$
#4660
0$
#4665
b11101010 "
b11101010 )
b11101001 #
b11101001 *
#4670
1$
#4680
0$
#4685
b11101011 "
b11101011 )
b11101010 #
b11101010 *
#4690
1$
#4700
0$
#4705
b11101100 "
b11101100 )
b11101011 #
b11101011 *
#4710
1$
#4720
0$
#4725
b11101101 "
b11101101 )
b11101100 #
b11101100 *
#4730
1$
#4740
0$
#4745
b11101110 "
b11101110 )
b11101101 #
b11101101 *
#4750
1$
#4760
0$
#4765
b11101111 "
b11101111 )
b11101110 #
b11101110 *
#4770
1$
#4780
0$
#4785
b11110000 "
b11110000 )
b11101111 #
b11101111 *
#4790
1$
#4800
0$
#4805
b11110001 "
b11110001 )
b11110000 #
b11110000 *
#4810
1$
#4820
0$
#4825
b11110010 "
b11110010 )
b11110001 #
b11110001 *
#4830
1$
#4840
0$
#4845
b11110011 "
b11110011 )
b11110010 #
b11110010 *
#4850
1$
#4860
0$
#4865
b11110100 "
b11110100 )
b11110011 #
b11110011 *
#4870
1$
#4880
0$
#4885
b11110101 "
b11110101 )
b11110100 #
b11110100 *
#4890
1$
#4900
0$
#4905
b11110110 "
b11110110 )
b11110101 #
b11110101 *
#4910
1$
#4920
0$
#4925
b11110111 "
b11110111 )
b11110110 #
b11110110 *
#4930
1$
#4940
0$
#4945
b11111000 "
b11111000 )
b11110111 #
b11110111 *
#4950
1$
#4960
0$
#4965
b11111001 "
b11111001 )
b11111000 #
b11111000 *
#4970
1$
#4980
0$
#4985
b11111010 "
b11111010 )
b11111001 #
b11111001 *
#4990
1$
#5000
0$
#5005
b11111011 "
b11111011 )
b11111010 #
b11111010 *
#5010
1$
#5020
0$
#5025
b11111100 "
b11111100 )
b11111011 #
b11111011 *
#5030
1$
#5040
0$
#5045
b11111101 "
b11111101 )
b11111100 #
b11111100 *
#5050
1$
#5060
0$
#5065
b11111110 "
b11111110 )
b11111101 #
b11111101 *
#5070
1$
#5080
0$
#5085
b11111111 "
b11111111 )
b11111110 #
b11111110 *
#5090
1$
#5100
0$
#5105
b0 "
b0 )
b11111111 #
b11111111 *
#5110
1$
#5120
0$
#5125
b1 !
b1 +
b0 (
1&
b0 #
b0 *
#5130
1$
#5140
0$
#5145
b10 !
b10 +
b1 (
b1 #
b1 *
#5150
1$
#5160
0$
#5165
b11 !
b11 +
b10 (
b10 #
b10 *
#5170
1$
#5180
0$
#5185
b100 !
b100 +
b11 (
b11 #
b11 *
#5190
1$
#5200
0$
#5205
b101 !
b101 +
b100 (
b100 #
b100 *
#5210
1$
#5220
0$
#5225
b110 !
b110 +
b101 (
b101 #
b101 *
#5230
1$
#5240
0$
#5245
b111 !
b111 +
b110 (
b110 #
b110 *
#5250
1$
#5260
0$
#5265
b1000 !
b1000 +
b111 (
b111 #
b111 *
#5270
1$
#5280
0$
#5285
b1001 !
b1001 +
b1000 (
b1000 #
b1000 *
#5290
1$
#5300
0$
#5305
b1010 !
b1010 +
b1001 (
b1001 #
b1001 *
#5310
1$
#5320
0$
#5325
b1011 !
b1011 +
b1010 (
b1010 #
b1010 *
#5330
1$
#5340
0$
#5345
b1100 !
b1100 +
b1011 (
b1011 #
b1011 *
#5350
1$
#5360
0$
#5365
b1101 !
b1101 +
b1100 (
b1100 #
b1100 *
#5370
1$
#5380
0$
#5385
b1110 !
b1110 +
b1101 (
b1101 #
b1101 *
#5390
1$
#5400
0$
#5405
b1111 !
b1111 +
b1110 (
b1110 #
b1110 *
#5410
1$
#5420
0$
#5425
b10000 !
b10000 +
b1111 (
b1111 #
b1111 *
#5430
1$
#5440
0$
#5445
b10001 !
b10001 +
b10000 (
b10000 #
b10000 *
#5450
1$
#5460
0$
#5465
b10010 !
b10010 +
b10001 (
b10001 #
b10001 *
#5470
1$
#5480
0$
#5485
b10011 !
b10011 +
b10010 (
b10010 #
b10010 *
#5490
1$
#5500
0$
#5505
b10100 !
b10100 +
b10011 (
b10011 #
b10011 *
#5510
1$
#5520
0$
#5525
b10101 !
b10101 +
b10100 (
b10100 #
b10100 *
#5530
1$
#5540
0$
#5545
b10110 !
b10110 +
b10101 (
b10101 #
b10101 *
#5550
1$
#5560
0$
#5565
b10111 !
b10111 +
b10110 (
b10110 #
b10110 *
#5570
1$
#5580
0$
#5585
b11000 !
b11000 +
b10111 (
b10111 #
b10111 *
#5590
1$
#5600
0$
#5605
b11001 !
b11001 +
b11000 (
b11000 #
b11000 *
#5610
1$
#5620
0$
#5625
b11010 !
b11010 +
b11001 (
b11001 #
b11001 *
#5630
1$
#5640
0$
#5645
b11011 !
b11011 +
b11010 (
b11010 #
b11010 *
#5650
1$
#5660
0$
#5665
b11100 !
b11100 +
b11011 (
b11011 #
b11011 *
#5670
1$
#5680
0$
#5685
b11101 !
b11101 +
b11100 (
b11100 #
b11100 *
#5690
1$
#5700
0$
#5705
b11110 !
b11110 +
b11101 (
b11101 #
b11101 *
#5710
1$
#5720
0$
#5725
b11111 !
b11111 +
b11110 (
b11110 #
b11110 *
#5730
1$
#5740
0$
#5745
b100000 !
b100000 +
b11111 (
b11111 #
b11111 *
#5750
1$
#5760
0$
#5765
b100001 !
b100001 +
b100000 (
b100000 #
b100000 *
#5770
1$
#5780
0$
#5785
b100010 !
b100010 +
b100001 (
b100001 #
b100001 *
#5790
1$
#5800
0$
#5805
b100011 !
b100011 +
b100010 (
b100010 #
b100010 *
#5810
1$
#5820
0$
#5825
b100100 !
b100100 +
b100011 (
b100011 #
b100011 *
#5830
1$
#5840
0$
#5845
b100101 !
b100101 +
b100100 (
b100100 #
b100100 *
#5850
1$
#5860
0$
#5865
b100110 !
b100110 +
b100101 (
b100101 #
b100101 *
#5870
1$
#5880
0$
#5885
b100111 !
b100111 +
b100110 (
b100110 #
b100110 *
#5890
1$
#5900
0$
#5905
b101000 !
b101000 +
b100111 (
b100111 #
b100111 *
#5910
1$
#5920
0$
#5925
b101001 !
b101001 +
b101000 (
b101000 #
b101000 *
#5930
1$
#5940
0$
