Design/seq_8.v
/*
MODULE OVETVIEW 
This module is a 8 bit sequnce detector which detects the seqence
loaded manually.
*/

module seq_8(
 input clk,				//clock.
 input rst, 			//reset active high.
 input load,			//load input to change between u_data and s_data state.
 input din,				//serial input.
 output reg dout		//output.
 );

reg din_buff; 		  	//act as input buffer.
reg [7:0] data ;		  //register to store the user data.
reg [3:0] counter ;		//counter.
reg [2:0] ps, ns ;		//present state and next state.

parameter idle = 3'b001, u_data = 3'b010, s_data = 3'b100 ; 	//states.

always@(posedge clk)			//syncronous part
begin : syn_pro
 if(rst == 1'b1) begin
  ps <= idle ;					    //idle on reset.
  data <= 8'bzzzzzzzz ;			//high impedance state when reset.
 end

 else 	
  ps <= ns ;					//state change.
end

always@(*)
  din_buff <= din ;

always@(ps, load, din_buff)						//combinatorial part.
begin : com_pro
 

 case(ps)
  idle : begin
  		  counter = 4'b0000 ;
  		  if(load == 1)						//accept the sequence from the user.
  	       ns = u_data ;
  		  else ns = idle;
  		 end

  u_data : begin 							//data by user is stored.
  		    data[counter] <= din_buff ;		//8 bit sequnce stored in data register.
  		    counter = counter + 4'b0001 ;	//counter to specify the position.

  		    if(counter == 4'b1000)			
  		   	 ns = idle ;					//when 8 bits are taken goes to idle.
  		    else ns = u_data ;
  		   end

  s_data : begin 									             //serial data accepted from din.
   			if(din_buff == data[counter]) begin 	 //checks input serial data with data register.
   			  counter = counter + 4'b001 ;			
   			   if(counter == 4'b1000)				
   			    dout = 1 ;							         //if the sequence is same then output 1.
   			   else dout = 0 ;					         //if sequence is not matching then output 0.
   			 end
   			else begin 
			  counter = 4'b0000 ;				        	//counter is reset.
			  dout = 0 ;
			 end

			 ns = s_data ;						           //stay in the same state until reset is high.
		   end 

  default : begin
  			 dout = 0 ;
  			 ns = idle ;
  			 counter = 4'b0000 ;
  			end
 endcase
end 		//end of com block.



endmodule

Testbenches/seq_8_test.v
// test bench for sequence detector
//
//
module seq_8_test ;

 reg clk, rst, load, din;
 wire dout ;
 //reg [3:0] coun ;
 integer i;

 localparam period = 10;

 seq_8 uut (clk, rst, load, din, dout) ;

 initial begin
 $dumpfile("../Dumpfiles/seq_8_test.vcd");
 //$dumpfile("seq_8_test.vcd");
 $dumpvars(0, seq_8_test);

 rst = 1 ;
 clk = 0 ;
 load = 0 ;
 din = 0 ;
 #25 ;
  rst = 0 ;
  load = 1 ;
  for(i = 0 ; i < 4 ; i = i+1) begin
   #40 ;
    din = ~din ;
  end

  load = 0 ;

 #40 ;
  for(i = 0 ; i < 4 ; i = i+1) begin
   #40 ;
    din = ~din ;
  end

 #40 ;
  din = 1;
  $finish;
 #100;
 end

always
 #period clk = ~clk ;




endmodule

Dumpfiles/seq_8_test.vcd
$date
	Wed May  5 14:25:35 2021
$end
$version
	Icarus Verilog
$end
$timescale
	1s
$end
$scope module seq_8_test $end
$var wire 1 ! dout $end
$var reg 1 " clk $end
$var reg 1 # din $end
$var reg 1 $ load $end
$var reg 1 % rst $end
$var integer 32 & i [31:0] $end
$scope module uut $end
$var wire 1 " clk $end
$var wire 1 # din $end
$var wire 1 $ load $end
$var wire 1 % rst $end
$var reg 4 ' counter [3:0] $end
$var reg 8 ( data [7:0] $end
$var reg 1 ) din_buff $end
$var reg 1 ! dout $end
$var reg 3 * ns [2:0] $end
$var reg 3 + ps [2:0] $end
$scope begin com_pro $end
$upscope $end
$scope begin syn_pro $end
$upscope $end
$upscope $end
$upscope $end
$enddefinitions $end
#0
$dumpvars
bx +
b1 *
0)
bx (
b0 '
bx &
1%
0$
0#
0"
0!
$end
#10
bz (
b1 +
1"
#20
0"
#25
b10 *
b0 &
1$
0%
#30
bz0 (
b1 '
b10 +
1"
#40
0"
#50
1"
#60
0"
#65
bz10 (
b10 '
1)
b1 &
1#
#70
1"
#80
0"
#90
1"
#100
0"
#105
bz010 (
b11 '
0)
b10 &
0#
#110
1"
#120
0"
#130
1"
#140
0"
#145
bz1010 (
b100 '
1)
b11 &
1#
#150
1"
#160
0"
#170
1"
#180
0"
#185
bz011010 (
0)
b110 '
0$
b100 &
0#
#190
1"
#200
0"
#210
1"
#220
0"
#225
b0 &
#230
1"
#240
0"
#250
1"
#260
0"
#265
bz1011010 (
b111 '
1)
b1 &
1#
#270
1"
#280
0"
#290
1"
#300
0"
#305
b1011010 (
b1 *
b1000 '
0)
b10 &
0#
#310
b0 '
b1 +
1"
#320
0"
#330
1"
#340
0"
#345
1)
b11 &
1#
#350
1"
#360
0"
#370
1"
#380
0"
#385
0)
b100 &
0#
#390
1"
#400
0"
#410
1"
#420
0"
#425
1)
1#
