Design/seq_8.v
/*
MODULE OVERVIEW:
This module is a 8 bit sequnce detector which detects the seqence
loaded manually.
Operation:
1)Reset the module.
2)Then provide the sequence to be detected in the serial input port.
  At the same time, make sure that the load port is set to 1.
3)Observe serial output port. If the specified sequence arrives in the input
  port, then a HIGH value is written to the output port.
*/

module seq_8(
 input          clk,				//clock.
 input          rst_n, 			//reset active low.
 input          load,			  //load input to change between u_data and s_data state.
 input          din,				//serial input.
 output         dout		    //output.
 );

reg flag = 0;
reg [7:0] data;		         //register to store the user data.
reg [2:0] counter;         //counter.
reg [2:0] ps, ns;		       //present state and next state.

parameter idle = 3'b001, u_data = 3'b010, s_data = 3'b100 ; 	//states.

always@(posedge clk or negedge rst_n)			//syncronous part
begin : syn_pro
 if(~rst_n)
  ps <= idle ;					     //idle on reset.
 else
  ps <= ns ;					       //state change.
end


always @(posedge clk)
begin
 case(ps)
  idle:
  begin
   counter <= 3'd7;
   data <= 8'h00;
  end
  u_data:
  begin
   data[counter] <= din;                       //accept the sequence from the user.
   counter <= counter - 3'd1;
  end
  s_data:
  begin
   if(din == data[counter])                    //serial data in din is checked with corresponding bit in data.
    counter <= counter - 3'd1;
   else counter <= 3'd7;
  end
 endcase
end

always@(ps, load, din)						//combinatorial part.
begin : com_pro
 case(ps)
  idle : begin
  		    if(load == 1)
  	       ns = u_data ;
  		    else ns = idle;
  		   end
  u_data : begin
  		      if(counter == 3'd0)
  		   	   ns = s_data ;
  		      else ns = u_data ;
  		     end
  s_data : begin
            flag = ((counter == 3'd0) && (din == data[counter])) ? 1 : 0;
			      ns = s_data ;						           //stay in the same state until reset is high.
		       end
  default : ns = idle;
 endcase
end

assign dout = (flag) ? 1 : 0;

endmodule

Testbenches/seq_8_test.v
// test bench for sequence detector
//
//
module seq_8_test ;

 reg clk, rst_n, load, din;
 wire dout ;
 //reg [3:0] coun ;
 integer i;

 localparam period = 10;

 seq_8 uut (clk, rst_n, load, din, dout) ;

 initial begin
 $dumpfile("../Dumpfiles/seq_8_test.vcd");
 //$dumpfile("seq_8_test.vcd");
 $dumpvars(0, seq_8_test);

 rst_n = 0 ;
 clk = 0 ;
 load = 0 ;
 din = 0 ;
 #25 ;
  rst_n = 1 ;
  load = 1 ;
  for(i = 0 ; i < 4 ; i = i+1) begin
   #40 ;
    din = ~din ;
  end

  load = 0 ;

 #40 ;
  for(i = 0 ; i < 4 ; i = i+1) begin
   #40 ;
    din = ~din ;
  end

 #40 ;
  din = 1;
  $finish;
 #100;
 end

always
 #period clk = ~clk ;




endmodule

Dumpfiles/seq_8_test.vcd
$date
	Wed May  5 21:22:55 2021
$end
$version
	Icarus Verilog
$end
$timescale
	1s
$end
$scope module seq_8_test $end
$var wire 1 ! dout $end
$var reg 1 " clk $end
$var reg 1 # din $end
$var reg 1 $ load $end
$var reg 1 % rst_n $end
$var integer 32 & i [31:0] $end
$scope module uut $end
$var wire 1 " clk $end
$var wire 1 # din $end
$var wire 1 $ load $end
$var wire 1 % rst_n $end
$var wire 1 ! dout $end
$var reg 3 ' counter [2:0] $end
$var reg 8 ( data [7:0] $end
$var reg 1 ) flag $end
$var reg 3 * ns [2:0] $end
$var reg 3 + ps [2:0] $end
$scope begin com_pro $end
$upscope $end
$scope begin syn_pro $end
$upscope $end
$upscope $end
$upscope $end
$enddefinitions $end
#0
$dumpvars
b1 +
b1 *
0)
bx (
bx '
bx &
0%
0$
0#
0"
0!
$end
#10
b0 (
b111 '
1"
#20
0"
#25
b10 *
b0 &
1$
1%
#30
b10 +
1"
#40
0"
#50
b110 '
1"
#60
0"
#65
b1 &
1#
#70
b101 '
b1000000 (
1"
#80
0"
#90
b100 '
b1100000 (
1"
#100
0"
#105
b10 &
0#
#110
b11 '
1"
#120
0"
#130
b10 '
1"
#140
0"
#145
b11 &
1#
#150
b1 '
b1100100 (
1"
#160
0"
#170
b0 '
b1100110 (
1"
#180
0"
#185
b100 *
0$
b100 &
0#
#190
b111 '
b100 +
1"
#200
0"
#210
b110 '
1"
#220
0"
#225
b0 &
#230
b111 '
1"
#240
0"
#250
b110 '
1"
#260
0"
#265
b1 &
1#
#270
b101 '
1"
#280
0"
#290
b100 '
1"
#300
0"
#305
b10 &
0#
#310
b11 '
1"
#320
0"
#330
b10 '
1"
#340
0"
#345
b11 &
1#
#350
b1 '
1"
#360
0"
#370
b0 '
1"
#380
0"
#385
1!
1)
b100 &
0#
#390
b111 '
1"
#400
0"
#410
b110 '
1"
#420
0"
#425
0!
0)
1#
